library/__init__.py
awholenewworld-0.1.2.dist-info/LICENSE
awholenewworld-0.1.2.dist-info/METADATA
awholenewworld-0.1.2.dist-info/WHEEL
awholenewworld-0.1.2.dist-info/top_level.txt
awholenewworld-0.1.2.dist-info/RECORD
